{
  "fetched_at": "2026-05-04T01:22:04.743797+00:00",
  "total_articles": 142,
  "categories": {
    "world_and_markets": {
      "display_name": "World & Markets",
      "weight": 0.4,
      "subsections": {
        "Top Headlines": [
          {
            "id": "b9bc87cb57497a423626e6fc8027e7f4",
            "title": "Iran says US has responded to its latest peace proposal",
            "url": "https://www.bbc.com/news/articles/cn0px2x53k2o?at_medium=RSS&at_campaign=rss",
            "summary": "The US is yet to formally confirm it has responded. However, Trump reportedly told Israel's Kan News it was unacceptable.",
            "source": "BBC World",
            "published": "2026-05-03T21:28:09+00:00",
            "category": "world_and_markets",
            "subsection": "Top Headlines"
          },
          {
            "id": "70b131847c61583324021ad69e0376c6",
            "title": "The Iran war has strengthened Ukraine in surprising ways. Could a ceasefire with Russia be closer?",
            "url": "https://www.bbc.com/news/articles/cgjp7vpee03o?at_medium=RSS&at_campaign=rss",
            "summary": "President Zelensky has been visiting the Gulf to demonstrate his country's military nous.",
            "source": "BBC World",
            "published": "2026-05-02T23:19:27+00:00",
            "category": "world_and_markets",
            "subsection": "Top Headlines"
          },
          {
            "id": "54ccba76f5e46d6d0f10247dbcb3a460",
            "title": "Three dead in suspected virus outbreak on Atlantic cruise ship",
            "url": "https://www.bbc.com/news/articles/cy0294829ndo?at_medium=RSS&at_campaign=rss",
            "summary": "The World Health Organization said one case of hantavirus infection has been confirmed, with five more suspected cases under investigation.",
            "source": "BBC World",
            "published": "2026-05-03T22:13:36+00:00",
            "category": "world_and_markets",
            "subsection": "Top Headlines"
          },
          {
            "id": "a13c59db19d957b2855a601b40321a56",
            "title": "Russian strikes kill 10 as Zelensky says Ukraine hits oil tankers and terminal",
            "url": "https://www.bbc.com/news/articles/clyp41v1n1go?at_medium=RSS&at_campaign=rss",
            "summary": "Fatalities have been reported around Ukraine as Kyiv says Russian \"shadow fleet\" tankers were hit by drones.",
            "source": "BBC World",
            "published": "2026-05-03T13:43:20+00:00",
            "category": "world_and_markets",
            "subsection": "Top Headlines"
          },
          {
            "id": "97754ff273db077947a9d6a41a5cf8a8",
            "title": "Nigeria summons South African envoy over attacks on its nationals",
            "url": "https://www.bbc.com/news/articles/c78q6e98878o?at_medium=RSS&at_campaign=rss",
            "summary": "There has been a wave of anti-migrant protests in South Africa, some of which have turned violent.",
            "source": "BBC World",
            "published": "2026-05-03T10:16:01+00:00",
            "category": "world_and_markets",
            "subsection": "Top Headlines"
          },
          {
            "id": "123a930295cc7d14c9bf6e99ab2d809f",
            "title": "Police officer lowered into crocodile-infested river to recover human remains",
            "url": "https://www.bbc.com/news/articles/cz92gk18xn4o?at_medium=RSS&at_campaign=rss",
            "summary": "Police suspect the human remains belong to a businessman swept away by floodwater last week.",
            "source": "BBC World",
            "published": "2026-05-03T15:47:59+00:00",
            "category": "world_and_markets",
            "subsection": "Top Headlines"
          },
          {
            "id": "34fd924ce32b1ac148a576ae21235966",
            "title": "The clandestine network smuggling Starlink tech into Iran to beat internet blackout",
            "url": "https://www.bbc.com/news/articles/cvgzk91leweo?at_medium=RSS&at_campaign=rss",
            "summary": "Sahand tells the BBC World Service he sends satellite internet terminals into Iran to help show \"the real picture\".",
            "source": "BBC World",
            "published": "2026-05-02T23:17:17+00:00",
            "category": "world_and_markets",
            "subsection": "Top Headlines"
          },
          {
            "id": "5c9acc83f33b3db098121ecff2695937",
            "title": "Germany troop cuts send wrong signal to Russia, say two top US Republicans",
            "url": "https://www.bbc.com/news/articles/cewpx5yvwyxo?at_medium=RSS&at_campaign=rss",
            "summary": "The chairs of the House and Senate armed services committees said withdrawing 5,000 service personnel risked undermining deterrence.",
            "source": "BBC World",
            "published": "2026-05-03T08:41:23+00:00",
            "category": "world_and_markets",
            "subsection": "Top Headlines"
          },
          {
            "id": "d127507234b84ef4fa4ae900b007d5a2",
            "title": "Concern for jailed Iranian Nobel laureate as brother fears she is dying",
            "url": "https://www.bbc.com/news/articles/c362pd8epw9o?at_medium=RSS&at_campaign=rss",
            "summary": "Her family said the 54-year-old had been taken from prison to a local hospital after a sharp deterioration in her health.",
            "source": "BBC World",
            "published": "2026-05-03T14:44:04+00:00",
            "category": "world_and_markets",
            "subsection": "Top Headlines"
          },
          {
            "id": "a29f87c201fc5f3d26e85b85645cdf77",
            "title": "Two US service members reported missing in Morocco, officials say",
            "url": "https://www.bbc.com/news/articles/cn7prznmllko?at_medium=RSS&at_campaign=rss",
            "summary": "A search and rescue operation is underway for the service members, who are believed to have been involved in an accident, according to authorities.",
            "source": "BBC World",
            "published": "2026-05-03T17:27:21+00:00",
            "category": "world_and_markets",
            "subsection": "Top Headlines"
          },
          {
            "id": "917c7f2ebeb4f22ab1e8dc291944743a",
            "title": "Man charged with murder of 5-year-old Australian girl",
            "url": "https://www.bbc.com/news/articles/cy92qennznjo?at_medium=RSS&at_campaign=rss",
            "summary": "The girl's death sparked an outbreak of violence in the central Australian town from where she disappeared.",
            "source": "BBC World",
            "published": "2026-05-03T05:52:09+00:00",
            "category": "world_and_markets",
            "subsection": "Top Headlines"
          },
          {
            "id": "04a37181d2220633b552225774a0c8eb",
            "title": "Trump tells Congress ceasefire means he does not need their approval for Iran war",
            "url": "https://www.bbc.com/news/articles/c4g4xexy4w7o?at_medium=RSS&at_campaign=rss",
            "summary": "The president writes that hostilities \"have terminated\" because of the ceasefire, arguing he does not need congressional authorisation.",
            "source": "BBC World",
            "published": "2026-05-02T23:03:03+00:00",
            "category": "world_and_markets",
            "subsection": "Top Headlines"
          },
          {
            "id": "62874260037603ba4de33661887edebf",
            "title": "Who shot a Secret Service officer at the Trump press dinner?",
            "url": "https://www.bbc.com/news/articles/cm2pmk0r3pjo?at_medium=RSS&at_campaign=rss",
            "summary": "Court papers do not explicitly accuse the suspect of shooting the officer, even as officials say it was not \"friendly fire\".",
            "source": "BBC World",
            "published": "2026-05-03T17:29:13+00:00",
            "category": "world_and_markets",
            "subsection": "Top Headlines"
          },
          {
            "id": "758b98da798a8befa4c92456999618d7",
            "title": "Kenya battles to stop the 'goons and guns' as fears of political violence grow",
            "url": "https://www.bbc.com/news/articles/c9qdz0p0x5qo?at_medium=RSS&at_campaign=rss",
            "summary": "More than 100 gangs are operating nationwide as the growing use of political thugs raises fears of election violence.",
            "source": "BBC World",
            "published": "2026-05-03T06:57:44+00:00",
            "category": "world_and_markets",
            "subsection": "Top Headlines"
          },
          {
            "id": "d2a9173cfc3908eaf2d0ffc92499b9f1",
            "title": "Voters will judge Trump on the economy - how is it doing?",
            "url": "https://www.bbc.com/news/articles/cgepyv20vrpo?at_medium=RSS&at_campaign=rss",
            "summary": "How much Donald Trump can do with the time he has left as president will depend massively on the cost of living.",
            "source": "BBC World",
            "published": "2026-05-03T09:52:06+00:00",
            "category": "world_and_markets",
            "subsection": "Top Headlines"
          },
          {
            "id": "c5694a9b71fc5d56dbd7eebe23f6f60a",
            "title": "Laufey on making jazz cool again (and the fish that brought out her inner rage)",
            "url": "https://www.bbc.com/news/articles/c99lvggdy4jo?at_medium=RSS&at_campaign=rss",
            "summary": "The Icelandic star reflects on a phenomenal year, and the music video that let her go \"primal\".",
            "source": "BBC World",
            "published": "2026-05-02T23:05:34+00:00",
            "category": "world_and_markets",
            "subsection": "Top Headlines"
          },
          {
            "id": "db4227abd2e52c36c40171b9b46bcae5",
            "title": "Dragonflies in distress: Scientists sound alarm in India's ecological hotspot",
            "url": "https://www.bbc.com/news/articles/cx2107kzyreo?at_medium=RSS&at_campaign=rss",
            "summary": "A new study reveals a decline in dragonfly and damselfly species in India's Western Ghats.",
            "source": "BBC World",
            "published": "2026-05-02T22:13:11+00:00",
            "category": "world_and_markets",
            "subsection": "Top Headlines"
          },
          {
            "id": "9c7f3d5116f1611ce044b79e439902bd",
            "title": "Huge crowd attends free Shakira Copacabana beach concert",
            "url": "https://www.bbc.com/news/videos/c8r8j50zxnno?at_medium=RSS&at_campaign=rss",
            "summary": "Shakira's appearance followed shows by Lady Gaga and Madonna, who have also performed on Copacabana beach in previous years.",
            "source": "BBC World",
            "published": "2026-05-03T07:56:47+00:00",
            "category": "world_and_markets",
            "subsection": "Top Headlines"
          },
          {
            "id": "132ea917be424fa7eeaf84770fed24fa",
            "title": "How we reported in -30C temperatures in Canada's Arctic",
            "url": "https://www.bbc.com/news/videos/cvgz3pnn1ppo?at_medium=RSS&at_campaign=rss",
            "summary": "BBC's Nadine Yousif and Eloise Alanna spent five days travelling with the country's military rangers through frostbite and sub-zero temperatures.",
            "source": "BBC World",
            "published": "2026-05-03T04:30:41+00:00",
            "category": "world_and_markets",
            "subsection": "Top Headlines"
          },
          {
            "id": "787ed5a8b3741cc1c12ba8bdf3e13d06",
            "title": "Illegal \u2018free party\u2019 at French military site draws up to 40,000 ravers",
            "url": "https://www.aljazeera.com/video/newsfeed/2026/5/4/illegal-free-party-at-french-military-site-draws-up-to-40000-ravers?traffic_source=rss",
            "summary": "Tens of thousands of partygoers gathered for an illegal \u201cfree party\u201d at a military firing range near Bourges.",
            "source": "Al Jazeera English",
            "published": "2026-05-04T00:40:20+00:00",
            "category": "world_and_markets",
            "subsection": "Top Headlines"
          },
          {
            "id": "bed9fac460b747cb15906933070627f2",
            "title": "Iran war live: Tehran warns Trump\u2019s Hormuz mission violates ceasefire",
            "url": "https://www.aljazeera.com/news/liveblog/2026/5/4/iran-war-live-tehran-says-trumps-hormuz-mission-violates-ceasefire?traffic_source=rss",
            "summary": "Iran protests as Trump announces &#039;Project Freedom&#039; to escort stranded ships out of the Strait of Hormuz.",
            "source": "Al Jazeera English",
            "published": "2026-05-04T00:00:00+00:00",
            "category": "world_and_markets",
            "subsection": "Top Headlines"
          },
          {
            "id": "30656a1841cd0a761a389604fd3098be",
            "title": "Thousands in India\u2019s Manipur mark three years since ethnic clashes began",
            "url": "https://www.aljazeera.com/video/newsfeed/2026/5/3/thousands-in-indias-manipur-mark-three-years-since-ethnic-clashes-began?traffic_source=rss",
            "summary": "Thousands of protesters gathered in India\u2019s Manipur state to mark three years since ethnic violence erupted.",
            "source": "Al Jazeera English",
            "published": "2026-05-03T23:04:52+00:00",
            "category": "world_and_markets",
            "subsection": "Top Headlines"
          },
          {
            "id": "22ac2bb030cb0317914606d8d242672d",
            "title": "Three dead in suspected hantavirus outbreak on Atlantic cruise ship",
            "url": "https://www.aljazeera.com/news/2026/5/3/three-dead-in-suspected-hantavirus-outbreak-on-atlantic-cruise-ship?traffic_source=rss",
            "summary": "Three of six passengers ill from a suspected rodent-transmitted virus have died, and one is in intensive care, WHO says.",
            "source": "Al Jazeera English",
            "published": "2026-05-03T21:59:20+00:00",
            "category": "world_and_markets",
            "subsection": "Top Headlines"
          },
          {
            "id": "1d5ca10a6623cb627448f98488e5d625",
            "title": "French left-wing\u2019s Melenchon says he will run for president in 2027",
            "url": "https://www.aljazeera.com/news/2026/5/3/french-left-wings-melenchon-says-he-will-run-for-president-in-2027?traffic_source=rss",
            "summary": "Melenchon says he will make fourth bid for presidency with President Macron term-limited and Le Pen facing ban.",
            "source": "Al Jazeera English",
            "published": "2026-05-03T21:25:48+00:00",
            "category": "world_and_markets",
            "subsection": "Top Headlines"
          },
          {
            "id": "c68cc3c1635b7fcb0aedf7ce493ef830",
            "title": "Real Madrid stays alive in La Liga title race with victory at Espanyol",
            "url": "https://www.aljazeera.com/sports/2026/5/3/real-madrid-stays-alive-in-la-liga-title-race-with-victory-at-espanyol?traffic_source=rss",
            "summary": "Two goals by Vinicius Jr allowed Madrid to remain in title contention with Barcelona ahead of El Clasico next Sunday.",
            "source": "Al Jazeera English",
            "published": "2026-05-03T21:22:15+00:00",
            "category": "world_and_markets",
            "subsection": "Top Headlines"
          },
          {
            "id": "1d9e99bf8c108af41c47c10b200d7208",
            "title": "Iran lawmaker says Strait of Hormuz will not return to pre\u2011war state",
            "url": "https://www.aljazeera.com/video/newsfeed/2026/5/3/iran-lawmaker-says-strait-of-hormuz-will-not-return-to-pre%e2%80%91war-state?traffic_source=rss",
            "summary": "Iran says the Strait of Hormuz will never return to the status quo that existed before the US-Israel war on Tehran.",
            "source": "Al Jazeera English",
            "published": "2026-05-03T20:51:57+00:00",
            "category": "world_and_markets",
            "subsection": "Top Headlines"
          },
          {
            "id": "150b9065fe311dff09acb813e45c4c01",
            "title": "Trump says US will \u2018help free up\u2019 ships stuck in Hormuz Strait",
            "url": "https://www.aljazeera.com/news/2026/5/3/trump-says-us-will-help-free-up-ships-stuck-in-hormuz-strait?traffic_source=rss",
            "summary": "US president says any interference with operation, which will start on Monday, will &#039;have to be dealt with forcefully&#039;.",
            "source": "Al Jazeera English",
            "published": "2026-05-03T20:47:14+00:00",
            "category": "world_and_markets",
            "subsection": "Top Headlines"
          },
          {
            "id": "66b5120ab4ca70d6f86b4067a612a6cd",
            "title": "Is Mali\u2019s military government losing control?",
            "url": "https://www.aljazeera.com/video/inside-story/2026/5/3/is-malis-military-government-losing-control?traffic_source=rss",
            "summary": "A coalition of armed groups and rebels challenges the military government&#039;s authority.",
            "source": "Al Jazeera English",
            "published": "2026-05-03T20:30:59+00:00",
            "category": "world_and_markets",
            "subsection": "Top Headlines"
          },
          {
            "id": "4b8e62b1c4226a27caba5cd35c1690a7",
            "title": "Kimi Antonelli wins Miami GP to extend F1 title lead",
            "url": "https://www.aljazeera.com/sports/2026/5/3/kimi-antonelli-wins-miami-grand-prix-to-extend-f1-title-lead?traffic_source=rss",
            "summary": "Nineteen-year-old becomes the first driver in F1 history to convert his first three pole positions into race victories.",
            "source": "Al Jazeera English",
            "published": "2026-05-03T20:28:51+00:00",
            "category": "world_and_markets",
            "subsection": "Top Headlines"
          },
          {
            "id": "dbd1cc22fc3c9732335741a85ad205ff",
            "title": "World Press Freedom Day marked in Gaza as journalist death toll rises",
            "url": "https://www.aljazeera.com/video/newsfeed/2026/5/3/world-press-freedom-day-marked-in-gaza-as-journalist-death-toll-rises?traffic_source=rss",
            "summary": "Palestinian journalists in Gaza marked World Press Freedom Day by honouring colleagues killed and targeted by Israel.",
            "source": "Al Jazeera English",
            "published": "2026-05-03T20:07:00+00:00",
            "category": "world_and_markets",
            "subsection": "Top Headlines"
          },
          {
            "id": "b7d8aba3f4f09e3c1f5ea35a904dd19c",
            "title": "Is Israel expanding into Gaza despite ceasefire?",
            "url": "https://www.aljazeera.com/video/upfront/2026/5/3/is-israel-expanding-into-gaza-despite-ceasefire?traffic_source=rss",
            "summary": "Redi Tlhabi speaks to Ray Adams Row Farr from Forensic Architecture about Israel\u2019s expansion into Gaza post-ceasefire.",
            "source": "Al Jazeera English",
            "published": "2026-05-03T19:55:02+00:00",
            "category": "world_and_markets",
            "subsection": "Top Headlines"
          },
          {
            "id": "795f2cfc42bc1afeb4a362ab152df425",
            "title": "Germany\u2019s Merz downplays rift with Washington despite US troop drawdown",
            "url": "https://www.aljazeera.com/economy/2026/5/3/germanys-merz-downplays-rift-with-washington-despite-us-troop-drawdown?traffic_source=rss",
            "summary": "German chancellor says criticism of Donald Trump&#039;s strategy in Iran unrelated to troop withdrawal announcement.",
            "source": "Al Jazeera English",
            "published": "2026-05-03T19:42:55+00:00",
            "category": "world_and_markets",
            "subsection": "Top Headlines"
          },
          {
            "id": "d5693ce62d0e59f8c863209a2bcd158a",
            "title": "Israel\u2019s strategy of \u2018permanent war\u2019: A race against time?",
            "url": "https://www.aljazeera.com/video/the-bottom-line/2026/5/3/israels-strategy-of-permanent-war-a-race-against-time?traffic_source=rss",
            "summary": "Political analyst Daniel Levy says US policy is so \u2018marinated\u2019 in Israeli narratives, the two are indistinguishable.",
            "source": "Al Jazeera English",
            "published": "2026-05-03T19:36:54+00:00",
            "category": "world_and_markets",
            "subsection": "Top Headlines"
          },
          {
            "id": "c8c4e77be003bd984de0fbd1a3ed8cae",
            "title": "Israeli forces kill Palestinian man in raid on Nablus in occupied West Ban",
            "url": "https://www.aljazeera.com/video/newsfeed/2026/5/3/israeli-forces-kill-palestinian-man-in-raid-on-nablus-in-occupied-west-ban?traffic_source=rss",
            "summary": "Israeli forces have raided the city of Nablus in the occupied West Bank, killing a 26-year-old man.",
            "source": "Al Jazeera English",
            "published": "2026-05-03T17:52:00+00:00",
            "category": "world_and_markets",
            "subsection": "Top Headlines"
          },
          {
            "id": "7b748d1071bd098825613595b7d3a9ff",
            "title": "Investigators say Trump assassination suspect shot officer at press gala",
            "url": "https://www.aljazeera.com/news/2026/5/3/investigators-say-trump-assassination-suspect-shot-officer-at-press-gala?traffic_source=rss",
            "summary": "Secret Service agent at White House correspondents&#039; dinner was &#039;definitively&#039; hit by suspect&#039;s bullet, prosecutor says.",
            "source": "Al Jazeera English",
            "published": "2026-05-03T17:25:50+00:00",
            "category": "world_and_markets",
            "subsection": "Top Headlines"
          },
          {
            "id": "ba318dae668f7c4b3faf3fb42745451c",
            "title": "Floods and landslides kill at least 18 in Kenya",
            "url": "https://www.aljazeera.com/news/2026/5/3/floods-and-landslides-kill-at-least-18-in-kenya?traffic_source=rss",
            "summary": "Ongoing rains are causing floods and landslides in the East African nation.",
            "source": "Al Jazeera English",
            "published": "2026-05-03T17:04:33+00:00",
            "category": "world_and_markets",
            "subsection": "Top Headlines"
          },
          {
            "id": "cea40cdedfafdbfe3dfa56f7fcceaa3b",
            "title": "Manchester United beat Liverpool to secure Champions League qualification",
            "url": "https://www.aljazeera.com/sports/2026/5/3/man-united-beat-liverpool-3-2-to-secure-champions-league-qualification?traffic_source=rss",
            "summary": "Kobbie Mainoo&#039;s late strike earns a thrilling victory after bitter rivals Liverpool had fought back from two goals down.",
            "source": "Al Jazeera English",
            "published": "2026-05-03T16:54:08+00:00",
            "category": "world_and_markets",
            "subsection": "Top Headlines"
          },
          {
            "id": "85c40ba82c75922ed826c52d16e24d21",
            "title": "Bulk carrier attacked by multiple small craft off Iran, UKMTO says",
            "url": "https://www.aljazeera.com/news/2026/5/3/bulk-carrier-attacked-by-multiple-small-craft-off-iran-ukmto-says?traffic_source=rss",
            "summary": "Crew is safe and no environmental impact has been reported after the incident 11 nautical miles (20km) west of Sirik.",
            "source": "Al Jazeera English",
            "published": "2026-05-03T16:47:24+00:00",
            "category": "world_and_markets",
            "subsection": "Top Headlines"
          },
          {
            "id": "e0b03d61619466fa7e0c66d411565a1c",
            "title": "The US vs Latin America: Varsha Gandikota and Susana Muhamad",
            "url": "https://www.aljazeera.com/video/reframe/2026/5/3/the-us-v-latin-america-varsha-gandikota-susana-muhamad?traffic_source=rss",
            "summary": "Gandikota asks Muhamad: What does the military\u2011industrial machine mean for the sovereignty of the Global South?",
            "source": "Al Jazeera English",
            "published": "2026-05-03T15:58:20+00:00",
            "category": "world_and_markets",
            "subsection": "Top Headlines"
          },
          {
            "id": "f2212a16e47e07fe4562dc7cf25b0eda",
            "title": "Israel threatens Gaza war resumption to force disarmament as \u2018truce\u2019 frays",
            "url": "https://www.aljazeera.com/news/2026/5/3/israel-threatens-gaza-war-resumption-to-force-disarmament-as-truce-frays?traffic_source=rss",
            "summary": "Palestinian factions reject US-backed plans linking aid to weapons surrender, demanding clear political path forward.",
            "source": "Al Jazeera English",
            "published": "2026-05-03T15:40:46+00:00",
            "category": "world_and_markets",
            "subsection": "Top Headlines"
          },
          {
            "id": "0bb2c00453a47c92ba61882202b655c3",
            "title": "Zelenskyy has no cards to play against Russia or the West",
            "url": "https://www.aljazeera.com/opinions/2026/5/3/zelenskyy-has-no-cards-to-play-against-russia-or-the-west?traffic_source=rss",
            "summary": "The president seems unable to secure for Ukrainian people a gain that can compensate for a painful peace.",
            "source": "Al Jazeera English",
            "published": "2026-05-03T15:09:01+00:00",
            "category": "world_and_markets",
            "subsection": "Top Headlines"
          },
          {
            "id": "2c8700b4a914b854dd4a6e6441a3f35b",
            "title": "On World Press Freedom Day, Pope honours journalists killed in war zones",
            "url": "https://www.aljazeera.com/news/2026/5/3/pope-honors-journalists-killed-in-war-zones-on-world-press-freedom-day?traffic_source=rss",
            "summary": "Pope Leo XIV asks faithful to remember journalists who have lost their lives pursuing the truth.",
            "source": "Al Jazeera English",
            "published": "2026-05-03T14:06:20+00:00",
            "category": "world_and_markets",
            "subsection": "Top Headlines"
          },
          {
            "id": "2dd059b8bfd69cef5daadb35dec0738f",
            "title": "Who are the two Gaza flotilla activists abducted by Israel?",
            "url": "https://www.aljazeera.com/news/2026/5/3/who-are-the-two-gaza-flotilla-activists-abducted-by-israel?traffic_source=rss",
            "summary": "Spanish national Saif Abu Keshek and Brazilian Thiago Avila were among 175 Gaza flotilla activists detained by Israel.",
            "source": "Al Jazeera English",
            "published": "2026-05-03T14:00:03+00:00",
            "category": "world_and_markets",
            "subsection": "Top Headlines"
          },
          {
            "id": "40265756036fc45ccca540ba09bedaec",
            "title": "US to cut troops in Germany as Iran war spat deepens",
            "url": "https://www.aljazeera.com/video/newsfeed/2026/5/3/us-to-cut-troops-in-germany-as-iran-war-spat-deepens?traffic_source=rss",
            "summary": "US-German relations are straining as a spat deepens between President Trump and Chancellor Merz over the war on Iran.",
            "source": "Al Jazeera English",
            "published": "2026-05-03T13:38:56+00:00",
            "category": "world_and_markets",
            "subsection": "Top Headlines"
          },
          {
            "id": "06b4669268bcba6ee73659f6879cba8e",
            "title": "Trump says US will help free ships stuck in Strait of Hormuz",
            "url": "https://www.politico.com/news/2026/05/03/trump-free-ships-strait-of-hormuz-00904160?utm_source=RSS_Feed&utm_medium=RSS&utm_campaign=RSS_Syndication",
            "summary": "The U.S. will work to guide vessels out of the strait beginning Monday morning, according to the president\u2019s announcement.",
            "source": "Politico EU",
            "published": "2026-05-03T23:24:41+00:00",
            "category": "world_and_markets",
            "subsection": "Top Headlines"
          },
          {
            "id": "cb17172442b1ce464c51530910eb4a72",
            "title": "Merz shrugs off Trump clash over troops, trade",
            "url": "https://www.politico.eu/article/friedrich-merz-shrugs-trump-clash-troop-withdrawal-trade-relationship-sours/?utm_source=RSS_Feed&utm_medium=RSS&utm_campaign=RSS_Syndication",
            "summary": "Merz publicly wonders if he could have handled Trump better, but doesn't plan to change his style to be more \"polished.\"",
            "source": "Politico EU",
            "published": "2026-05-03T21:49:59+00:00",
            "category": "world_and_markets",
            "subsection": "Top Headlines"
          },
          {
            "id": "8ee97d64d6a3c93e10bc3172faa57bfc",
            "title": "Left-wing M\u00e9lenchon announces 2027 run for French presidency",
            "url": "https://www.politico.eu/article/france-left-wing-candidate-jean-luc-melenchon-announces-fourth-run-president-2027/?utm_source=RSS_Feed&utm_medium=RSS&utm_campaign=RSS_Syndication",
            "summary": "One of the most polarizing figures in French politics, M\u00e9lenchon narrowly missed the runoff in the last two presidential elections.",
            "source": "Politico EU",
            "published": "2026-05-03T19:43:49+00:00",
            "category": "world_and_markets",
            "subsection": "Top Headlines"
          },
          {
            "id": "a2e0949fe7ff089be84c06325ac79737",
            "title": "FIFA faces the World Cup\u2019s toughest opponent: New Jersey",
            "url": "https://www.politico.com/news/2026/05/03/fifa-new-jersey-world-cup-00896497?utm_source=RSS_Feed&utm_medium=RSS&utm_campaign=RSS_Syndication",
            "summary": "FIFA got what it wanted from dictators and oil sheikhs. Elected politicians in the Garden State are proving harder to please.",
            "source": "Politico EU",
            "published": "2026-05-03T18:27:59+00:00",
            "category": "world_and_markets",
            "subsection": "Top Headlines"
          },
          {
            "id": "21d851ee08f7fa33e1750083537a6d4c",
            "title": "Poland\u2019s president plans constitution rewrite",
            "url": "https://www.politico.eu/article/poland-president-karol-nawrocki-constitution-rewrite/?utm_source=RSS_Feed&utm_medium=RSS&utm_campaign=RSS_Syndication",
            "summary": "Polish Prime Minister Donald Tusk suggested the president start abiding by the current constitution instead.",
            "source": "Politico EU",
            "published": "2026-05-03T13:42:06+00:00",
            "category": "world_and_markets",
            "subsection": "Top Headlines"
          },
          {
            "id": "fc6010d9088a86e727145e6e5831ff47",
            "title": "US\u2019s Rubio to visit Italy after Trump\u2019s spats with Meloni, Pope Leo",
            "url": "https://www.politico.eu/article/rubio-italy-after-trump-spats-meloni-pope-leo-thaw-weak-tajani-rome-vatican/?utm_source=RSS_Feed&utm_medium=RSS&utm_campaign=RSS_Syndication",
            "summary": "The May 7-8 trip comes hot on the heels of Trump's criticism of the pope and the Italian leader.",
            "source": "Politico EU",
            "published": "2026-05-03T11:39:35+00:00",
            "category": "world_and_markets",
            "subsection": "Top Headlines"
          },
          {
            "id": "807630dd87b75981906f015d74dff6b7",
            "title": "Madrid demands release of Spanish-Swedish activist detained by Israel",
            "url": "https://www.politico.eu/article/spain-release-activist-saif-abukeshek-israel/?utm_source=RSS_Feed&utm_medium=RSS&utm_campaign=RSS_Syndication",
            "summary": "Spanish Prime Minister Pedro S\u00e1nchez said activist Saif Abukeshek had been \"illegally abducted by the Netanyahu government.\"",
            "source": "Politico EU",
            "published": "2026-05-03T10:05:56+00:00",
            "category": "world_and_markets",
            "subsection": "Top Headlines"
          },
          {
            "id": "51e5da01ee09269a75eda636891cf84b",
            "title": "US to cut troop presence in Germany \u2018a lot further than 5,000,\u2019 Trump says",
            "url": "https://www.politico.eu/article/us-to-cut-troop-presence-in-germany-a-lot-further-than-5000-trump-says/?utm_source=RSS_Feed&utm_medium=RSS&utm_campaign=RSS_Syndication",
            "summary": "\u201cWe\u2019re going to cut way down,\u201d Trump told reporters in Florida, escalating a dispute with German Chancellor Friedrich Merz.",
            "source": "Politico EU",
            "published": "2026-05-03T07:24:37+00:00",
            "category": "world_and_markets",
            "subsection": "Top Headlines"
          },
          {
            "id": "4fa175d53dac023b81b6ffd369f52edc",
            "title": "Trump casts doubt on Iran\u2019s new peace proposal",
            "url": "https://www.politico.eu/article/trump-casts-doubt-on-irans-new-peace-proposal/?utm_source=RSS_Feed&utm_medium=RSS&utm_campaign=RSS_Syndication",
            "summary": "The president rejected a previous Iranian proposal, but conversations have continued.",
            "source": "Politico EU",
            "published": "2026-05-03T06:27:44+00:00",
            "category": "world_and_markets",
            "subsection": "Top Headlines"
          },
          {
            "id": "3aca14d9d187dafff809390432381e3f",
            "title": "New US surgeon general nominee has a MAHA problem",
            "url": "https://www.politico.com/news/2026/05/02/casey-means-maha-surgeon-general-nicole-saphier-00903761?utm_source=RSS_Feed&utm_medium=RSS&utm_campaign=RSS_Syndication",
            "summary": "Nicole Saphier, a radiologist and former Fox News medical contributor, is a more conventional pick than Casey Means, the previous nominee.",
            "source": "Politico EU",
            "published": "2026-05-03T05:19:56+00:00",
            "category": "world_and_markets",
            "subsection": "Top Headlines"
          }
        ],
        "US-China Relations": [
          {
            "id": "f97d6dfee9e5c3068408bb20379713de",
            "title": "Nvidia expands Asian partnerships, eyes largest market cap by June 30",
            "url": "https://cryptobriefing.com/nvidia-expands-asian-partnerships-eyes-largest-market-cap-by-june-30/",
            "summary": "Nvidia's strategic Asian partnerships could reshape global tech dynamics, challenging US-China trade norms and impacting market leadership.\nThe post Nvidia expands Asian partnerships, eyes largest market cap by June 30 appeared first on Crypto Briefing.",
            "source": "Crypto Briefing",
            "published": "2026-05-03T00:57:48Z",
            "category": "world_and_markets",
            "subsection": "US-China Relations"
          },
          {
            "id": "fb82d6cab9f129c0be5f6f7d7ab3b85b",
            "title": "China blocks Meta\u2019s acquisition of Chinese-founded AI startup Manus",
            "url": "https://www.cnn.com/2026/04/27/tech/china-blocks-meta-manus-intl-hnk",
            "summary": "China blocked Meta's $2 billion acquisition of AI startup Manus, citing fears of losing technology to the U.S., highlighting growing U.S.-China tech tensions and the increasingly restrictive environment for cross-border deals in critical sectors.",
            "source": "CNN",
            "published": "2026-05-03T00:00:00Z",
            "category": "world_and_markets",
            "subsection": "US-China Relations"
          },
          {
            "id": "8a7ece5d83377094ab3d2f53818813bb",
            "title": "Power crisis: Stakeholders push renewable energy",
            "url": "https://punchng.com/power-crisis-stakeholders-push-renewable-energy/",
            "summary": "Stakeholders in Nigeria advocate for renewable energy to solve the nation\u2019s power crisis, discussing challenges, new tech, and improved service delivery.\n\nRead More: https://punchng.com/power-crisis-stakeholders-push-renewable-energy/",
            "source": "The Punch",
            "published": "2026-05-02T23:52:56Z",
            "category": "world_and_markets",
            "subsection": "US-China Relations"
          }
        ],
        "Financial Markets": [
          {
            "id": "01a1478fda46f537c4eac420bab10a06",
            "title": "Stock futures are little changed as investors monitor latest in U.S.-Iran developments: Live updates",
            "url": "https://www.cnbc.com/2026/05/03/stock-market-today-live-updates.html",
            "summary": "The S&amp;P 500 and Nasdaq Composite are coming off of a solid week, having notched fresh records on Friday.",
            "source": "CNBC",
            "published": "2026-05-03T23:08:05+00:00",
            "category": "world_and_markets",
            "subsection": "Financial Markets"
          },
          {
            "id": "48864b969afbe77995174309fbe21d8c",
            "title": "Oil prices fall in choppy trade as Trump plans to 'free' ships stranded due to Mideast conflict",
            "url": "https://www.cnbc.com/2026/05/04/oil-prices-today-wti-brent-trump-iran-us-hormuz.html",
            "summary": "The United Kingdom Maritime Trade Operations agency said Monday that a tanker was hit by projectiles north of the city of of Fujairah in the United Arab Emirates.",
            "source": "CNBC",
            "published": "2026-05-04T00:58:48+00:00",
            "category": "world_and_markets",
            "subsection": "Financial Markets"
          },
          {
            "id": "88090796e6ca7d202b0cf1f509de1ec8",
            "title": "Trump says U.S. will 'free' ships trapped in Persian Gulf by Strait of Hormuz closure",
            "url": "https://www.cnbc.com/2026/05/03/trump-iran-strait-of-hormuz-trapped-ships.html",
            "summary": "Vessels have been largely unable to pass through the Strait of Hormuz for months, disrupting key supply chains.",
            "source": "CNBC",
            "published": "2026-05-03T23:53:10+00:00",
            "category": "world_and_markets",
            "subsection": "Financial Markets"
          },
          {
            "id": "842601ff09a8a396f0f67b1ea8f93404",
            "title": "Pirro reveals new Trump attack evidence; Cole Allen removed from 'suicide precautions'",
            "url": "https://www.cnbc.com/2026/05/03/trump-assassination-cole-allen-suicide-pirro.html",
            "summary": "Until U.S. Attorney Jeanine Pirro's comments, prosecutors had not disclosed whose bullet hit the agent.",
            "source": "CNBC",
            "published": "2026-05-03T23:44:38+00:00",
            "category": "world_and_markets",
            "subsection": "Financial Markets"
          },
          {
            "id": "f85be500a985b41320fcc568e7d850ce",
            "title": "Earnings playbook: Palantir and Advanced Micro Devices usher in the next week of reports",
            "url": "https://www.cnbc.com/2026/05/03/earnings-playbook-palantir-and-advanced-micro-devices-usher-in-the-next-week-of-reports.html",
            "summary": "Palantir, Advanced Micro Devices, Walt Disney and McDonald's are among the companies set to report.",
            "source": "CNBC",
            "published": "2026-05-03T11:10:18+00:00",
            "category": "world_and_markets",
            "subsection": "Financial Markets"
          },
          {
            "id": "a634d41dffd00053440e77b2622052da",
            "title": "'Godspeed my friend': Inside the final hours of Spirit Airlines",
            "url": "https://www.cnbc.com/2026/05/02/spirit-airlines-shutdown-inside-the-final-hours.html",
            "summary": "Spirit Airlines ceased operations overnight after a failed government bailout.",
            "source": "CNBC",
            "published": "2026-05-03T14:58:24+00:00",
            "category": "world_and_markets",
            "subsection": "Financial Markets"
          },
          {
            "id": "ed549cacc36308d4a90a323a0684b918",
            "title": "South Korean stocks hit fresh record, building on historic monthly rally in April",
            "url": "https://www.cnbc.com/2026/05/04/asia-markets-live-updates-today-hang-seng-kospi-asx-oil-us-iran-trump-hormuz.html",
            "summary": "Asia markets were set to open mixed Monday as investors assess news of President Donald Trump's plan to \"free\" ships stranded in the Strait of Hormuz.",
            "source": "CNBC",
            "published": "2026-05-04T00:20:00+00:00",
            "category": "world_and_markets",
            "subsection": "Financial Markets"
          },
          {
            "id": "ab139c8b8e6b1d506609064fbb0ed8a5",
            "title": "U.S. crude oil exports surge to record as tankers flock to Gulf Coast during Iran war",
            "url": "https://www.cnbc.com/2026/05/03/us-crude-oil-exports-surge-to-record-as-tankers-flock-to-gulf-coast.html",
            "summary": "Oil exports are booming from the U.S. Gulf Coast thanks to the Middle East supply disruption caused by the Iran war.",
            "source": "CNBC",
            "published": "2026-05-03T11:08:46+00:00",
            "category": "world_and_markets",
            "subsection": "Financial Markets"
          },
          {
            "id": "5369c54f659b5c28fd971bd0b7cb8e23",
            "title": "Chinese stocks are about to get a big AI boost, Morgan Stanley predicts",
            "url": "https://www.cnbc.com/2026/05/03/chinese-stocks-are-about-to-get-a-big-ai-boost-morgan-stanley-predicts.html",
            "summary": "The investment bank also raised its price targets on two Chinese companies that develop artificial intelligence models.",
            "source": "CNBC",
            "published": "2026-05-03T11:11:39+00:00",
            "category": "world_and_markets",
            "subsection": "Financial Markets"
          },
          {
            "id": "607521e72b489c7ec87a6224ea3d8dcd",
            "title": "Used EV sales are surging \u2014 how their ownership costs compare to gas-powered cars",
            "url": "https://www.cnbc.com/2026/05/03/ev-ownership-costs.html",
            "summary": "With more affordable electric vehicles hitting used-car lots, buyers should be aware of some ownership costs that may differ from those that come with gas cars.",
            "source": "CNBC",
            "published": "2026-05-03T13:30:01+00:00",
            "category": "world_and_markets",
            "subsection": "Financial Markets"
          },
          {
            "id": "1e45852f82f8bfbd38e99420472eabb5",
            "title": "Fewer features, more value: Why some Americans are buying simpler cars",
            "url": "https://www.cnbc.com/2026/05/03/why-some-americans-are-buying-simpler-cars.html",
            "summary": "Cloth seats, manual controls and analog gauges are back as buyers look for cars with sticker prices closer to $30,000.",
            "source": "CNBC",
            "published": "2026-05-03T13:00:01+00:00",
            "category": "world_and_markets",
            "subsection": "Financial Markets"
          },
          {
            "id": "803baa800953afca11fe23d36b78fdbe",
            "title": "Greg Abel earns solid scorecard from Berkshire shareholders after first annual meeting",
            "url": "https://www.cnbc.com/2026/05/03/berkshire-ceo-greg-abel-earns-solid-first-scorecard-after-first-annual-meeting.html",
            "summary": "The reviews from longtime shareholders and professional investors were broadly positive, even as many acknowledged the notable absence of Warren Buffett.",
            "source": "CNBC",
            "published": "2026-05-03T21:14:08+00:00",
            "category": "world_and_markets",
            "subsection": "Financial Markets"
          },
          {
            "id": "2df0c569c6df8fa23ea2663c5169391f",
            "title": "Pirro appears to drop plans to appeal criminal investigation of Fed Chair Powell",
            "url": "https://www.cnbc.com/2026/05/03/pirro-fed-powell.html",
            "summary": "The U.S. attorney shifted legal strategies in her investigation of Federal Reserve Chairman Jerome Powell just ahead of a deadline.",
            "source": "CNBC",
            "published": "2026-05-03T18:58:42+00:00",
            "category": "world_and_markets",
            "subsection": "Financial Markets"
          },
          {
            "id": "6658d768bde31a3e5c55660f5dce0f2d",
            "title": "Iran says it has received U.S. response to its latest offer for peace talks",
            "url": "https://www.cnbc.com/2026/05/03/trump-iran-war-peace-proposal.html",
            "summary": "The U.S. and Iran appear no closer to ending a war that has disrupted energy supplies, roiled world markets and raised fears about a global economic downturn.",
            "source": "CNBC",
            "published": "2026-05-03T18:08:25+00:00",
            "category": "world_and_markets",
            "subsection": "Financial Markets"
          },
          {
            "id": "3bc7c533557f89ccfb46df10a709e4d1",
            "title": "OPEC+ announces 188,000 barrels-per-day output increase in first meeting without UAE",
            "url": "https://www.cnbc.com/2026/05/03/opec-announces-188000-barrels-per-day-output-increase-.html",
            "summary": "Concerns around production were amplified further last week with news of the UAE's shock departure.",
            "source": "CNBC",
            "published": "2026-05-03T11:28:54+00:00",
            "category": "world_and_markets",
            "subsection": "Financial Markets"
          },
          {
            "id": "a1097aeb8c79ae2a6d595ed128e9fe02",
            "title": "Greg Abel rules out Berkshire break-up, stresses continuity with Buffett's legacy at annual meeting",
            "url": "https://www.cnbc.com/2026/05/03/berkshire-annual-meeting-greg-abel-rules-out-break-up-stressing-continuity-with-buffett.html",
            "summary": "New CEO Greg Abel did most of the talking at his first Berkshire Hathaway shareholders meeting, but Warren Buffett was still a major presence.",
            "source": "CNBC",
            "published": "2026-05-03T23:14:58+00:00",
            "category": "world_and_markets",
            "subsection": "Financial Markets"
          },
          {
            "id": "8ce9e735ea19c94f3327660afadfa4df",
            "title": "JPMorgan's Jamie Dimon issued vague credit recession warning, but the bond market has more pressing issues",
            "url": "https://www.cnbc.com/2026/05/02/kevin-warsh-federal-reserve-interest-rates-bonds-fixed-income.html",
            "summary": "As fears about a credit crisis rise, bond investors may be too complacent with Kevin Warsh to become next Fed chair and volatility in rates likely to follow.",
            "source": "CNBC",
            "published": "2026-05-02T23:23:07+00:00",
            "category": "world_and_markets",
            "subsection": "Financial Markets"
          },
          {
            "id": "311ae72a922f4a316f0a7e10c892e7a0",
            "title": "Top Wall Street analysts like these 3 stocks for their long-term prospects",
            "url": "https://www.cnbc.com/2026/05/03/top-street-analysts-like-these-3-stocks-for-their-long-term-prospects.html",
            "summary": "The recommendations and analysis of these Wall Street experts can provide useful insights for stock selection.",
            "source": "CNBC",
            "published": "2026-05-03T11:13:01+00:00",
            "category": "world_and_markets",
            "subsection": "Financial Markets"
          },
          {
            "id": "13b4988c4e8b323db526fdfd6a22599f",
            "title": "Big Tech earnings show how big, smart spending can be rewarded by the market",
            "url": "https://www.cnbc.com/2026/05/03/big-tech-earnings-show-how-big-smart-spending-can-be-rewarded-by-the-market.html",
            "summary": "It's obvious from this quarter that the bubble talk has been proven wrong.",
            "source": "CNBC",
            "published": "2026-05-03T22:31:09+00:00",
            "category": "world_and_markets",
            "subsection": "Financial Markets"
          },
          {
            "id": "063c2794356baed823b2c87428e41df4",
            "title": "Healthcare cost surge makes parental paid leave benefits a target for workplace cuts",
            "url": "https://www.cnbc.com/2026/05/03/healthcare-costs-parental-paid-leave-employee-benefits-cuts.html",
            "summary": "As healthcare costs soar and companies search for savings, generous paid parental leave is a benefit being cut, with recent examples from Zoom and Deloitte.",
            "source": "CNBC",
            "published": "2026-05-03T14:14:40+00:00",
            "category": "world_and_markets",
            "subsection": "Financial Markets"
          },
          {
            "id": "6065c9a82168b6d91ea93a2159cd0b06",
            "title": "Spirit Airlines shuts down after failing to reach a bailout deal, ending discount travel era",
            "url": "https://www.cnbc.com/2026/05/01/spirit-airlines-trump-bailout.html",
            "summary": "Talks with bondholders for a government bailout this week failed to yield a deal.",
            "source": "CNBC",
            "published": "2026-05-02T23:07:35+00:00",
            "category": "world_and_markets",
            "subsection": "Financial Markets"
          },
          {
            "id": "0d129e3668b8d6fd56a7b51569a23dc0",
            "title": "Israel approves plan to buy F-35 and F-15IA fighter jets from Lockheed, Boeing",
            "url": "https://www.cnbc.com/2026/05/03/israel-approves-plan-to-buy-fighter-jets-from-lockheed-boeing.html",
            "summary": "The deal is a first step in a $119 billion plan to bolster Israel's military",
            "source": "CNBC",
            "published": "2026-05-03T09:20:55+00:00",
            "category": "world_and_markets",
            "subsection": "Financial Markets"
          },
          {
            "id": "0b4593f4923722fe3bfce5e2d074ec48",
            "title": "Golden Tempo wins thrilling Kentucky Derby as trainer DeVaux breaks barrier",
            "url": "https://www.cnbc.com/2026/05/02/kentucky-derby-golden-tempo.html",
            "summary": "Golden Tempo stormed to victory at the 152nd running of the\u00a0Kentucky\u00a0Derby\u00a0at Churchill Downs on Saturday.",
            "source": "CNBC",
            "published": "2026-05-03T10:04:07+00:00",
            "category": "world_and_markets",
            "subsection": "Financial Markets"
          }
        ],
        "Science & Technology Breakthroughs": []
      }
    },
    "ai_and_technology": {
      "display_name": "AI & Technology",
      "weight": 0.3,
      "subsections": {
        "Research & Papers": [],
        "Industry News": [
          {
            "id": "097973c08445b973635445e0a23bed6c",
            "title": "\u2018This is fine\u2019 creator says AI startup stole his art",
            "url": "https://techcrunch.com/2026/05/03/this-is-fine-creator-says-ai-startup-stole-his-art/",
            "summary": "The ad comes from Artisan, the AI startup behind billboards urging businesses to \"stop hiring humans.\"",
            "source": "TechCrunch AI",
            "published": "2026-05-03T20:16:51+00:00",
            "category": "ai_and_technology",
            "subsection": "Industry News"
          },
          {
            "id": "83edc1536074b836358a39f0421fb76a",
            "title": "In Harvard study, AI offered more accurate emergency room diagnoses than two human doctors",
            "url": "https://techcrunch.com/2026/05/03/in-harvard-study-ai-offered-more-accurate-diagnoses-than-emergency-room-doctors/",
            "summary": "A new study examines how large language models perform in a variety of medical contexts, including real emergency room cases \u2014 where at least one model seemed to be more accurate than human doctors.",
            "source": "TechCrunch AI",
            "published": "2026-05-03T18:00:09+00:00",
            "category": "ai_and_technology",
            "subsection": "Industry News"
          },
          {
            "id": "b9a998074991b776df4a1ea4cabb9af7",
            "title": "AI-generated actors and scripts are now ineligible for Oscars",
            "url": "https://techcrunch.com/2026/05/02/ai-generated-actors-and-scripts-are-now-ineligible-for-oscars/",
            "summary": "Bad news for Tilly Norwood.",
            "source": "TechCrunch AI",
            "published": "2026-05-02T21:54:58+00:00",
            "category": "ai_and_technology",
            "subsection": "Industry News"
          },
          {
            "id": "9f2f21811ef34ea1d2f98d7687e54c57",
            "title": "How the internet\u2019s favorite squirrel dad made the hottest camera app of 2026",
            "url": "https://www.theverge.com/tech/921690/dualshot-recorder-iphone-camera-app-derrick-downey-jr",
            "summary": "It's not hyperbole to call DualShot Recorder an overnight sensation. It took only 12 hours from the time it was released to hit number one on the App Store's list of top paid apps. It was a surprise success - but what's even more surprising is the app's origin story: it all started with a [&#8230;]",
            "source": "The Verge AI",
            "published": "2026-05-03T13:00:00+00:00",
            "category": "ai_and_technology",
            "subsection": "Industry News"
          },
          {
            "id": "44c2d8e2173cf548a9159032c2cb4cf5",
            "title": "AI music is flooding streaming services \u2014 but who wants it?",
            "url": "https://www.theverge.com/column/921599/ai-music-is-flooding-streaming-services-but-who-wants-it",
            "summary": "This is The Stepback, a weekly newsletter breaking down one essential story from the tech world. For more on how AI is changing music and the music industry, follow Terrence O'Brien. The Stepback arrives in our subscribers' inboxes at 8AM ET. Opt in for The Stepback here. How it started The use of generative AI [&#8230;]",
            "source": "The Verge AI",
            "published": "2026-05-03T12:00:00+00:00",
            "category": "ai_and_technology",
            "subsection": "Industry News"
          }
        ],
        "Key People & Company Updates": [
          {
            "id": "c64d597796b352987506872cb6bc7613",
            "title": "Google is now a glorified venture-capital fund thanks to its SpaceX and Anthropic stakes - MarketWatch",
            "url": "https://slashdot.org/firehose.pl?op=view&amp;id=183107638",
            "summary": "Google is now a glorified venture-capital fund thanks to its SpaceX and Anthropic stakesMarketWatch Half of Google's and Amazon's 'blowout AI profits\u2019 came from a stake in Anthropic\u2014not from their actual businessFortune Google\u2019s business did great \u2014 its inves\u2026",
            "source": "Slashdot.org",
            "published": "2026-05-03T00:32:59Z",
            "category": "ai_and_technology",
            "subsection": "Key People & Company Updates"
          },
          {
            "id": "b8c406bfe51b8f4c420c72e5c547f570",
            "title": "robot-resources 0.3.0",
            "url": "https://pypi.org/project/robot-resources/0.3.0/",
            "summary": "Robot Resources Python SDK \u2014 smart model selection for AI agents. Thin client over /v1/route + opt-in auto-attach for Anthropic, OpenAI, and Google Generative AI SDKs (set RR_AUTOATTACH=1).",
            "source": "Pypi.org",
            "published": "2026-05-02T22:44:31Z",
            "category": "ai_and_technology",
            "subsection": "Key People & Company Updates"
          },
          {
            "id": "caf23411af18c41748697072173462ac",
            "title": "robot-resources 0.2.0",
            "url": "https://pypi.org/project/robot-resources/0.2.0/",
            "summary": "Robot Resources Python SDK \u2014 smart model selection for AI agents. Thin client over /v1/route + opt-in auto-attach for the Anthropic SDK (set RR_AUTOATTACH=1).",
            "source": "Pypi.org",
            "published": "2026-05-02T22:12:18Z",
            "category": "ai_and_technology",
            "subsection": "Key People & Company Updates"
          },
          {
            "id": "7cf319a1289c9935f74340c0de61d2d0",
            "title": "agentlens-tracer added to PyPI",
            "url": "https://pypi.org/project/agentlens-tracer/",
            "summary": "The interactive debugger for LLM agents. Pause, inspect, and fork any agent mid-run.",
            "source": "Pypi.org",
            "published": "2026-05-02T21:32:38Z",
            "category": "ai_and_technology",
            "subsection": "Key People & Company Updates"
          }
        ]
      }
    },
    "private_equity_and_vc": {
      "display_name": "Private Equity & VC",
      "weight": 0.18,
      "subsections": {
        "Deals & Fundraising": [],
        "Fund News & Trends": [
          {
            "id": "d43083a054c93e784389f35bab4a5046",
            "title": "NAB CEO Says Business Bank Clients Face Challenge on Economy",
            "url": "https://www.bloomberg.com/news/articles/2026-05-03/nab-profit-misses-estimates-as-software-costs-weigh-on-bank",
            "summary": "National Australia Bank Ltd. Chief Executive Officer Andrew Irvine highlighted the challenges facing customers in its largest division after the lender missed first-half profit estimates on higher software costs and the deteriorating economy pushed up credit provisions.",
            "source": "Bloomberg",
            "published": "2026-05-03T22:11:55+00:00",
            "category": "private_equity_and_vc",
            "subsection": "Fund News & Trends"
          },
          {
            "id": "8d03332c2537b79a12213582f18ddb46",
            "title": "Pepperstone's Wu on Opportunities Amid Energy Disruption",
            "url": "https://www.bloomberg.com/news/videos/2026-05-04/pepperstone-s-wu-on-opportunities-amid-energy-disruption-video",
            "summary": "Pepperstone Group's Dilin Wu the path of oil is still \"pointing to the upside\", adding that Korean and Japanese equities are supported by bullish sentiment on AI potential. She describes herself as \"cautiously optimistic\" on these markets, noting the enduring persistence of risk factors. (Source: Bloomberg)",
            "source": "Bloomberg",
            "published": "2026-05-04T01:14:40+00:00",
            "category": "private_equity_and_vc",
            "subsection": "Fund News & Trends"
          },
          {
            "id": "e71a00da022fbefa292ea526d9a75f35",
            "title": "Asian Stocks Advance on Tech, Dollar Edges Lower: Markets Wrap",
            "url": "https://www.bloomberg.com/news/articles/2026-05-03/us-futures-gain-oil-falls-on-signs-of-iran-talks-markets-wrap",
            "summary": "Asian shares climbed as strong corporate earnings kept the technology sector buoyant, while oil fluctuated with mixed signals from the Middle East.",
            "source": "Bloomberg",
            "published": "2026-05-03T22:16:33+00:00",
            "category": "private_equity_and_vc",
            "subsection": "Fund News & Trends"
          },
          {
            "id": "305e9fc2c151c9cd8d2a97bd78e53c92",
            "title": "A2 Milk Recalls Batches of US Baby Formula After Toxin Find",
            "url": "https://www.bloomberg.com/news/articles/2026-05-03/a2-milk-recalls-batches-of-us-baby-formula-after-detecting-toxin",
            "summary": "New Zealand infant formula maker a2 Milk Co. is recalling batches of product sold in the US after detecting a toxin linked to vomiting and nausea, marking its first brush with a contamination scare that has rattled the global industry.",
            "source": "Bloomberg",
            "published": "2026-05-03T21:28:00+00:00",
            "category": "private_equity_and_vc",
            "subsection": "Fund News & Trends"
          },
          {
            "id": "94ceb5c3bc9f28ac4af3917eaf40ac50",
            "title": "Meme Stock GameStop Pitches $56 Billion Takeover of eBay",
            "url": "https://www.bloomberg.com/news/articles/2026-05-03/gamestop-making-56-billion-offer-to-acquire-ebay-wsj-says",
            "summary": "GameStop Corp. is proposing to buy eBay Inc. for about $56 billion in cash and stock, a bold attempt by Ryan Cohen to take over a storied e-commerce name several times larger.",
            "source": "Bloomberg",
            "published": "2026-05-03T23:09:05+00:00",
            "category": "private_equity_and_vc",
            "subsection": "Fund News & Trends"
          },
          {
            "id": "04cb5e5dc27820d00b67dcf5a81b0a25",
            "title": "Oil Steadies With Trump\u2019s Hormuz Plan and Tanker Attack in Focus",
            "url": "https://www.bloomberg.com/news/articles/2026-05-03/latest-oil-market-news-and-analysis-for-may-4",
            "summary": "Oil steadied as traders doubted the effectiveness of a plan by President Donald Trump for the US to guide neutral ships out through the Strait of Hormuz, with a tanker reportedly hit in the waterway.",
            "source": "Bloomberg",
            "published": "2026-05-03T22:01:43+00:00",
            "category": "private_equity_and_vc",
            "subsection": "Fund News & Trends"
          },
          {
            "id": "44af7454973f7f33289ebcff61c22e18",
            "title": "Takaichi Visits Australia to Bolster Economic, Defense Ties",
            "url": "https://www.bloomberg.com/news/articles/2026-05-03/takaichi-set-for-australia-visit-to-strengthen-japan-alliance",
            "summary": "Japan\u2019s prime minister is visiting Australia to strengthen ties with one of her country\u2019s strongest allies as she seeks to build on an updated regional strategy laid out in Vietnam.",
            "source": "Bloomberg",
            "published": "2026-05-03T07:13:05+00:00",
            "category": "private_equity_and_vc",
            "subsection": "Fund News & Trends"
          },
          {
            "id": "19d35d46e59aa50d3670cb3bbca15734",
            "title": "Philippines Accuses Chinese Ships of Illegal Marine Research",
            "url": "https://www.bloomberg.com/news/articles/2026-05-03/philippines-accuses-china-of-conducting-illegal-marine-research",
            "summary": "The Philippine Coast Guard said four Chinese vessels were conducting illegal marine scientific research in its waters and threatened to deploy aircraft and boats to repel them.",
            "source": "Bloomberg",
            "published": "2026-05-03T06:52:41+00:00",
            "category": "private_equity_and_vc",
            "subsection": "Fund News & Trends"
          },
          {
            "id": "c1f85e9da7e71e1bce281fb01a15456b",
            "title": "Trump: US to Start Guiding Trapped Ships Through Hormuz",
            "url": "https://www.bloomberg.com/news/videos/2026-05-04/trump-us-to-start-guiding-trapped-ships-through-hormuz-video",
            "summary": "President\u00a0Donald Trump\u00a0said the US will begin guiding some neutral ships trapped in the Persian Gulf out through the Strait of Hormuz starting Monday. Bloomberg's Tony Czuczka has the latest. (Source: Bloomberg)",
            "source": "Bloomberg",
            "published": "2026-05-04T00:07:46+00:00",
            "category": "private_equity_and_vc",
            "subsection": "Fund News & Trends"
          },
          {
            "id": "93a620e08d29ceed0e86296a92f00f59",
            "title": "Gold Steady With Focus on US Hormuz Plan And Iran Peace Talks",
            "url": "https://www.bloomberg.com/news/articles/2026-05-03/gold-steady-with-focus-on-hormuz-reopening-iran-peace-talks",
            "summary": "Gold was steady, after a second weekly decline, as traders monitored progress toward a US-Iran deal and President Donald Trump\u2019s plan to start guiding some ships through the Strait of Hormuz.",
            "source": "Bloomberg",
            "published": "2026-05-03T22:48:16+00:00",
            "category": "private_equity_and_vc",
            "subsection": "Fund News & Trends"
          },
          {
            "id": "ad559dae851b442109c332b55f207f0c",
            "title": "Hantavirus Outbreak on Cruise Ship Leaves 3 Dead, WHO Says",
            "url": "https://www.bloomberg.com/news/articles/2026-05-03/hantavirus-outbreak-on-cruise-ship-leaves-three-dead-who-says",
            "summary": "Three people have died and one is in intensive care in South Africa after a cluster of hantavirus infections linked to a cruise ship in the Atlantic Ocean, the World Health Organization said Sunday.",
            "source": "Bloomberg",
            "published": "2026-05-03T23:09:24+00:00",
            "category": "private_equity_and_vc",
            "subsection": "Fund News & Trends"
          },
          {
            "id": "7899cbc2da5f68dbab1b41d82e3c7f39",
            "title": "Block Trade King Simon Sadler Begins High-Profile Court Showdown",
            "url": "https://www.bloomberg.com/news/articles/2026-05-03/block-trade-king-simon-sadler-begins-high-profile-court-showdown",
            "summary": "The crowd at Bloomfield Road Stadium chanted Simon Sadler\u2019s name, giving the financier a hero\u2019s welcome.",
            "source": "Bloomberg",
            "published": "2026-05-03T23:00:00+00:00",
            "category": "private_equity_and_vc",
            "subsection": "Fund News & Trends"
          },
          {
            "id": "37a5a8edece64e3672f8e746cf55e259",
            "title": "Asia Bond Sales Jump in April as War Lull Spurs Rush in Issuance",
            "url": "https://www.bloomberg.com/news/articles/2026-05-03/asia-bond-sales-jump-in-april-as-war-lull-spurs-rush-in-issuance",
            "summary": "Asia-Pacific\u2019s dollar bond market saw its strongest April in five years as the start of a ceasefire in the Iran war opened the floodgates to a rush of issuance.",
            "source": "Bloomberg",
            "published": "2026-05-03T23:00:00+00:00",
            "category": "private_equity_and_vc",
            "subsection": "Fund News & Trends"
          },
          {
            "id": "8b85979e0ce6e7372ea73698596c3116",
            "title": "Aussie Rally May Fade as RBA Set to Temper Hikes, Analysts Say",
            "url": "https://www.bloomberg.com/news/articles/2026-05-03/aussie-rally-may-fade-as-rba-set-to-temper-hikes-analysts-say",
            "summary": "The Australian dollar\u2019s rally may fade with the Reserve Bank of Australia set to signal a slower pace of interest rate hikes after a widely expected increase this week, according to top forecasters.",
            "source": "Bloomberg",
            "published": "2026-05-03T22:18:14+00:00",
            "category": "private_equity_and_vc",
            "subsection": "Fund News & Trends"
          },
          {
            "id": "5354518ca8a6f61cdea60c8340f17e08",
            "title": "Mideast Peace Efforts in Focus as Trading Resumes: Markets Wrap",
            "url": "https://www.bloomberg.com/news/articles/2026-05-03/mideast-peace-efforts-in-focus-as-trading-resumes-markets-wrap",
            "summary": "The month-long surge in risky assets faces another test as investors gauge the viability of the latest Mideast truce proposals and await a key US employment report to assess the war\u2019s economic impact.",
            "source": "Bloomberg",
            "published": "2026-05-03T20:00:04+00:00",
            "category": "private_equity_and_vc",
            "subsection": "Fund News & Trends"
          },
          {
            "id": "b2a8ee2188735eaa424e5e346e1ee4c4",
            "title": "Trillions in Retirement Dollars Flow Into Opaque Trusts",
            "url": "https://www.bloomberg.com/news/features/2026-05-03/trillions-in-us-retirement-dollars-flow-into-opaque-trusts-that-rival-etfs",
            "summary": "A little-talked about investment product is taking over the 401(k) world, and offering asset managers a way to increase exposure to private markets.",
            "source": "Bloomberg",
            "published": "2026-05-03T21:00:18+00:00",
            "category": "private_equity_and_vc",
            "subsection": "Fund News & Trends"
          },
          {
            "id": "33b1ac70b9285107eff4c22a3be725f7",
            "title": "Trump Says US to Help Some Ships Leave Hormuz Starting Monday",
            "url": "https://www.bloomberg.com/news/articles/2026-05-03/trump-says-us-to-help-some-ships-leave-hormuz-starting-monday",
            "summary": "President Donald Trump says the US will help some ships leave Hormuz staring on Monday morning, Middle Eastern Time.",
            "source": "Bloomberg",
            "published": "2026-05-03T20:43:30+00:00",
            "category": "private_equity_and_vc",
            "subsection": "Fund News & Trends"
          },
          {
            "id": "e52c729e9a709004cf3366a9a69d2b4d",
            "title": "ECB\u2019s Stournaras Sees Recession Concern, Phileleftheros Says",
            "url": "https://www.bloomberg.com/news/articles/2026-05-03/ecb-s-stournaras-sees-recession-concern-phileleftheros-says",
            "summary": "Concern about a possible euro-area recession is \u201creal and justified\u201d as conflict in the Middle East causes a supply-side disruption, European Central Bank Governing Council member Yannis Stournaras said in an interview with Phileleftheros.",
            "source": "Bloomberg",
            "published": "2026-05-03T19:36:04+00:00",
            "category": "private_equity_and_vc",
            "subsection": "Fund News & Trends"
          },
          {
            "id": "b42a269f81af112df86cfbcf77611328",
            "title": "Treasury Market on Watch for Shift in Yellen-Era Debt Playbook",
            "url": "https://www.bloomberg.com/news/articles/2026-05-03/treasury-market-on-watch-for-shift-in-yellen-era-debt-playbook",
            "summary": "Wednesday will amount to a sort of Groundhog Day for US bond dealers, who will &mdash; as has been the case for more than a year now &mdash; be watching for any change in guidance from the Treasury in its latest plan for debt issuance.",
            "source": "Bloomberg",
            "published": "2026-05-03T19:00:01+00:00",
            "category": "private_equity_and_vc",
            "subsection": "Fund News & Trends"
          },
          {
            "id": "9c22c854ee6ad75579c4eb34b8f2893c",
            "title": "Bond Traders Look to Treasury Refunding, Fed Speakers and Jobs",
            "url": "https://www.bloomberg.com/news/articles/2026-05-03/bond-traders-look-to-treasury-refunding-fed-speakers-and-jobs",
            "summary": "US bond traders will focus on this week\u2019s announcement of the Treasury Department\u2019s borrowing plans for the next three months, an array of Federal Reserve speakers and a loaded calendar of economic releases crowned by monthly employment data.",
            "source": "Bloomberg",
            "published": "2026-05-03T19:00:00+00:00",
            "category": "private_equity_and_vc",
            "subsection": "Fund News & Trends"
          },
          {
            "id": "28d68685ce4838f9d881d80fee0747fc",
            "title": "Schumer Wants to Ban Lawmakers, Officials on Prediction Markets",
            "url": "https://www.bloomberg.com/news/articles/2026-05-03/schumer-says-house-white-house-must-ban-prediction-market-bets",
            "summary": "Senate Democratic leader Chuck Schumer called on the House of Representatives and the White House to follow the Senate\u2019s lead by imposing a ban on trading in fast-growing prediction markets.",
            "source": "Bloomberg",
            "published": "2026-05-03T18:27:15+00:00",
            "category": "private_equity_and_vc",
            "subsection": "Fund News & Trends"
          },
          {
            "id": "132a0069c1fa6ada8ec5d47bccc8dac3",
            "title": "Bloomberg This Weekend 5/3/2026",
            "url": "https://www.bloomberg.com/news/videos/2026-05-03/bloomberg-this-weekend-5-3-2026-video",
            "summary": "The news doesn\u2019t stop when markets close. Hosts David Gura, Christina Ruffini and Lisa Mateo bring clarity, context and a bit of humor to the weekend\u2019s biggest headlines, LIVE from New York. Joined by Chris Sununu, President and CEO of Airlines for America, Thomas Robinson, Domino Data Lab Chief Operating Officer, Maria Sharapova, Tennis Hall of Fame and Host of \u201cPretty Tough\u201d Podcast, Anna Gomez, Federal Communications Commission Commissioner, Rep. Kevin Kiley (I-CA), Rep. Cleo Fields (D-LA), A",
            "source": "Bloomberg",
            "published": "2026-05-03T17:18:20+00:00",
            "category": "private_equity_and_vc",
            "subsection": "Fund News & Trends"
          },
          {
            "id": "f4a1b6433bc658c662339c0acb0566f1",
            "title": "Rep. Kiley: Iran Cannot Be Allowed To Get A Nuclear Weapon",
            "url": "https://www.bloomberg.com/news/videos/2026-05-03/kiley-iran-cannot-be-allowed-to-get-a-nuclear-weapon-video",
            "summary": "Rep. Kevin Kiley (I-CA) joins David Gura and Christina Ruffini on Bloomberg This Weekend for a wide-ranging conversation on the Iran War, the collapse of Spirit Airlines and the impact of Supreme Court's decision in Louisiana v. Callais. Watch the full interview on Bloomberg This Weekend and watch the show LIVE every Saturday and Sunday morning. (Source: Bloomberg)",
            "source": "Bloomberg",
            "published": "2026-05-03T16:15:18+00:00",
            "category": "private_equity_and_vc",
            "subsection": "Fund News & Trends"
          },
          {
            "id": "805f586b1cba8c8d0072e3e72ad7266b",
            "title": "OPEC+ Agrees Symbolic Quota Hike as UAE Touts Oil Investment",
            "url": "https://www.bloomberg.com/news/articles/2026-05-03/opec-agrees-to-symbolic-june-quota-increase-delegates-say",
            "summary": "Major OPEC+ nations agreed on a modest and symbolic increase in their June production quota levels, as the group sends a business-as-usual message following the surprise exit of the United Arab Emirates. Abu Dhabi at the same moment touted its own growth plans.",
            "source": "Bloomberg",
            "published": "2026-05-03T10:27:47+00:00",
            "category": "private_equity_and_vc",
            "subsection": "Fund News & Trends"
          },
          {
            "id": "5148a06d0979449562f1ed3da5530534",
            "title": "FCC Commissioner Gomez Condemns Early ABC License Review as First Amendment Violation",
            "url": "https://www.bloomberg.com/news/videos/2026-05-03/fcc-condemns-early-abc-license-review-video",
            "summary": "Federal Communications Commission Commissioner Anna Gomez, the sole Democrat on the commission, joins David Gura and Christina Ruffini on Bloomberg This Weekend to discuss the FCC's decision to order an early review of ABC's local broadcast licenses, calling it an egregious violation of the First Amendment. Watch the full interview on Bloomberg This Weekend and watch the show LIVE every Saturday and Sunday morning. (Source: Bloomberg)",
            "source": "Bloomberg",
            "published": "2026-05-03T15:24:25+00:00",
            "category": "private_equity_and_vc",
            "subsection": "Fund News & Trends"
          },
          {
            "id": "7df8f2a1e099f702126333ac23031a81",
            "title": "Pointed News Quiz | AI, Marathon, Toys",
            "url": "https://www.bloomberg.com/news/videos/2026-05-03/pointed-news-quiz-ai-marathon-toys-video",
            "summary": "David Gura, Christina Ruffini, and Lisa Mateo of \u201cBloomberg This Weekend\u201d play Pointed! Wager your points, leverage your bets and answer wisely. A new quiz is available to play each week on Bloomberg.com. (Source: Bloomberg)",
            "source": "Bloomberg",
            "published": "2026-05-03T15:40:25+00:00",
            "category": "private_equity_and_vc",
            "subsection": "Fund News & Trends"
          },
          {
            "id": "8f171f8040eec0fe1cae5cbc9920804c",
            "title": "Bloomberg Dispatch: It\u2019s a Weird Time to Be Named Claude",
            "url": "https://www.bloomberg.com/news/videos/2026-05-03/bloomberg-dispatch-it-s-a-weird-time-to-be-named-claude-video",
            "summary": "The name Claude used to be a rare classic&mdash;now, it\u2019s a household name for a completely different reason. Ever since Anthropic launched its fast-growing AI assistant, humans named Claude have had to get used to sharing their identity with a chatbot. Bloomberg Senior feature writer Madison Darbyshire joins David Gura and Christina Ruffini on Bloomberg This Weekend to talk about her latest Dispatch, diving into the weird, funny, and occasionally annoying reality of what happens when your name ",
            "source": "Bloomberg",
            "published": "2026-05-03T15:35:00+00:00",
            "category": "private_equity_and_vc",
            "subsection": "Fund News & Trends"
          },
          {
            "id": "e7f1606f28eaf7d7757bfd08eefd431b",
            "title": "BTW | Goop Kitchen, Ozempic Breath, Hotspan",
            "url": "https://www.bloomberg.com/news/videos/2026-05-03/btw-goop-kitchen-ozempic-breath-hotspan-video",
            "summary": "Catch up on all the headlines with BTW. Lisa Mateo, Christina Ruffini and David Gura dive into the headlines you may have missed on Bloomberg This Weekend. Watch more here: Watch the show LIVE every Saturday and Sunday morning: (Source: Bloomberg)",
            "source": "Bloomberg",
            "published": "2026-05-03T15:03:36+00:00",
            "category": "private_equity_and_vc",
            "subsection": "Fund News & Trends"
          },
          {
            "id": "2c6d4322941a2ac2f9ffdfdf5c3b7645",
            "title": "Sharapova's 'Pretty Tough' Smashes Podcast Manosphere",
            "url": "https://www.bloomberg.com/news/videos/2026-05-03/sharapova-s-pretty-tough-smashes-podcast-manosphere-video",
            "summary": "Maria Sharapova made history in 2004, becoming the youngest tennis star to win a Grand Slam since Martina Hingis in 1997. Two decades later, the now hall-of-famer and mom joins Lisa Mateo on Bloomberg This Weekend to discuss venturing into a new arena - serving up compelling interviews for her new podcast 'Pretty Tough.' (Source: Bloomberg)",
            "source": "Bloomberg",
            "published": "2026-05-03T14:48:23+00:00",
            "category": "private_equity_and_vc",
            "subsection": "Fund News & Trends"
          },
          {
            "id": "8f4ecb990db6875334713ed5bf3fd45c",
            "title": "US to \u2018guide\u2019 stranded ships out of Strait of Hormuz, says Trump",
            "url": "https://www.ft.com/content/7ec081ca-3b1d-4fbe-b29a-a3b0b08efc41",
            "summary": "President says \u2018humanitarian\u2019 effort to begin on Monday as \u2018very positive discussions\u2019 continue with Iran",
            "source": "Financial Times",
            "published": "2026-05-04T01:06:04+00:00",
            "category": "private_equity_and_vc",
            "subsection": "Fund News & Trends"
          },
          {
            "id": "ca19dc86b5029bbb86b070799ace1a80",
            "title": "US pullback on long-range missiles leaves Europe exposed",
            "url": "https://www.ft.com/content/9651dfac-90c7-416f-bfcc-dfb1eaf0a9f7",
            "summary": "Cancelled deployment of weapons battalion as continent is re-arming threatens Nato deterrence against Russia",
            "source": "Financial Times",
            "published": "2026-05-03T19:26:31+00:00",
            "category": "private_equity_and_vc",
            "subsection": "Fund News & Trends"
          },
          {
            "id": "1913d924b572e8fde4cff24d27190ada",
            "title": "America\u2019s political identity crisis",
            "url": "https://www.ft.com/content/68f5fb2d-6434-47f2-bc5a-2115dd3c82a3",
            "summary": "The outer edges of both parties are overlapping on a growing number of issues",
            "source": "Financial Times",
            "published": "2026-05-03T12:00:05+00:00",
            "category": "private_equity_and_vc",
            "subsection": "Fund News & Trends"
          },
          {
            "id": "4e87c74c0ef7dddf9c2ffeee40d3d42e",
            "title": "Trump\u2019s green new deal",
            "url": "https://www.ft.com/content/fb275aae-355f-481f-ab30-999d861b7d42",
            "summary": "The US president\u2019s actions have inadvertently raised the appeal of renewable energy",
            "source": "Financial Times",
            "published": "2026-05-03T11:00:05+00:00",
            "category": "private_equity_and_vc",
            "subsection": "Fund News & Trends"
          },
          {
            "id": "a5538d0cea44c7354fcce30b1a83d530",
            "title": "Banks seek to offload risk to avoid \u2018choking\u2019 on data centre debt",
            "url": "https://www.ft.com/content/08aba5e4-5834-4e79-a48d-989a2c5bad0f",
            "summary": "Global lenders explore private deals and risk transfers to cut exposure to AI boom",
            "source": "Financial Times",
            "published": "2026-05-03T17:00:06+00:00",
            "category": "private_equity_and_vc",
            "subsection": "Fund News & Trends"
          },
          {
            "id": "9a8dc648d1864bf407587a699e87ab57",
            "title": "Greg Abel leaves unanswered questions about Berkshire\u2019s war chest",
            "url": "https://www.ft.com/content/ab525fb8-6de1-4f2d-b37f-52f23ad48eac",
            "summary": "Investors have been given few clues on the strategy of Warren Buffett\u2019s successor",
            "source": "Financial Times",
            "published": "2026-05-03T20:04:20+00:00",
            "category": "private_equity_and_vc",
            "subsection": "Fund News & Trends"
          },
          {
            "id": "8bbcc1d7ffa44f97d876247544643284",
            "title": "US Department of Justice loses a quarter of its lawyers",
            "url": "https://www.ft.com/content/a1316aae-83d9-4e2a-87aa-93de964bbbe0",
            "summary": "Thousands have quit or been fired since Trump returned to office with an agenda focused on immigrants and enemies",
            "source": "Financial Times",
            "published": "2026-05-03T10:00:05+00:00",
            "category": "private_equity_and_vc",
            "subsection": "Fund News & Trends"
          },
          {
            "id": "b22666de5c0547b53db21ef42a2bca7f",
            "title": "GameStop makes unsolicited $56bn offer for eBay",
            "url": "https://www.ft.com/content/31bfd02e-a02e-45fd-ad46-51544b1a3a8a",
            "summary": "The video game retailer is offering $125 a share for the resale web giant",
            "source": "Financial Times",
            "published": "2026-05-04T00:57:18+00:00",
            "category": "private_equity_and_vc",
            "subsection": "Fund News & Trends"
          },
          {
            "id": "de93bb7a59267af730cc175f5df736a9",
            "title": "Climate Change Weekly # 578\u2014 Countries and Industries Are Abandoning or Reducing Net-Zero Commitments",
            "url": "https://wattsupwiththat.com/2026/05/02/climate-change-weekly-578-countries-and-industries-are-abandoning-or-reducing-net-zero-commitments/",
            "summary": "Since the swearing-in of Donald Trump as the 47th president of the United States, climate alarmism and the political machinations in the public and private sector it spawned have experienced the death of a thousand cuts, described for centuries as a favorite \u2026",
            "source": "Wattsupwiththat.com",
            "published": "2026-05-03T01:00:00Z",
            "category": "private_equity_and_vc",
            "subsection": "Fund News & Trends"
          }
        ]
      }
    },
    "fintech": {
      "display_name": "Fintech",
      "weight": 0.12,
      "subsections": {
        "Platforms & Products": [
          {
            "id": "74ffb5f6e81d24de32940a82f3ba48e5",
            "title": "Wage Slowdown Leaves Gig Work Filling Pay Gaps",
            "url": "https://www.pymnts.com/economy/2026/wage-slowdown-leaves-gig-work-filling-pay-gaps/",
            "summary": "Wage growth is easing across the private sector, and the latest Employment Cost Index makes clear the deceleration is no longer a blip.  Private-sector wages and salaries rose 0.7% in the first quarter, according to data released April 30 from the Bureau of Labor Statistics. The broader wage measure increased 0.8%, while total compensation [&#8230;]\nThe post Wage Slowdown Leaves Gig Work Filling Pay Gaps appeared first on PYMNTS.com.",
            "source": "PYMNTS",
            "published": "2026-05-04T01:10:51+00:00",
            "category": "fintech",
            "subsection": "Platforms & Products"
          },
          {
            "id": "1a7b10a6b57c9acd48f17328d188a15d",
            "title": "Citi Debuts Platform to Bring AI Agents to Banking Work",
            "url": "https://www.pymnts.com/artificial-intelligence-2/2026/citi-debuts-platform-to-bring-ai-agents-to-banking-work/",
            "summary": "Banking giant Citi has debuted a platform to let it launch artificial intelligence agents throughout the company.  The agents created through the new Arc platform \u201cenhance human judgment by taking on tasks such as research, synthesis, preparation, and execution,\u201d Citi said in its announcement last week, thus \u201creducing manual effort and accelerating how teams [&#8230;]\nThe post Citi Debuts Platform to Bring AI Agents to Banking Work appeared first on PYMNTS.com.",
            "source": "PYMNTS",
            "published": "2026-05-04T00:52:18+00:00",
            "category": "fintech",
            "subsection": "Platforms & Products"
          },
          {
            "id": "750733abd9018ffbae8dcfe6cc07fee2",
            "title": "Fed\u2019s Barr Says Private Credit Stress Could Trigger Larger Credit Issues",
            "url": "https://www.pymnts.com/bank-regulation/2026/feds-barr-says-private-credit-stress-could-trigger-larger-credit-issues/",
            "summary": "Federal Reserve Governor Michael Barr is the latest official warning of private credit-related concerns.  Stress in that market could lead to \u201cpsychological contagion\u201d and thus set off a wider credit crunch, Barr said in an interview with Bloomberg News published Sunday (May 3). He told Bloomberg that although direct connections between banks and private [&#8230;]\nThe post Fed&#8217;s Barr Says Private Credit Stress Could Trigger Larger Credit Issues appeared first on PYMNTS.com.",
            "source": "PYMNTS",
            "published": "2026-05-04T00:31:54+00:00",
            "category": "fintech",
            "subsection": "Platforms & Products"
          },
          {
            "id": "5abb2de99977ee4d953b652ae4b83d59",
            "title": "Bessent Warns of Threat of AI-Powered Bank Account Hacks",
            "url": "https://www.pymnts.com/cybersecurity/2026/bessent-warns-of-threat-of-ai-powered-bank-account-hacks/",
            "summary": "Treasury Secretary Scott Bessent says American banks are working to safeguard against AI-related cyberthreats.  Bessent addressed the issue Sunday (May 3) in an interview with Fox News, coming in the wake of a meeting he and Federal Reserve Chair Jerome Powell held with Wall Street executives on concerns related to Anthropic\u2019s Mythos artificial intelligence [&#8230;]\nThe post Bessent Warns of Threat of AI-Powered Bank Account Hacks appeared first on PYMNTS.com.",
            "source": "PYMNTS",
            "published": "2026-05-04T00:10:31+00:00",
            "category": "fintech",
            "subsection": "Platforms & Products"
          },
          {
            "id": "fd45b79206c4ee4fed5a069cae445077",
            "title": "Verifone Owner in Talks to Buy Payments Firm Moneris",
            "url": "https://www.pymnts.com/acquisitions/2026/verifone-owner-in-talks-to-buy-payments-firm-moneris/",
            "summary": "A pair of Canadian banks is reportedly in talks to sell payments-focused FinTech Moneris.  The deal between Royal Bank of Canada and Bank of Montreal and the private equity firm Francisco Partners could value Moneris at more than $2 billion, the Financial Times (FT) reported Sunday (May 3), citing sources familiar with the matter. [&#8230;]\nThe post Verifone Owner in Talks to Buy Payments Firm Moneris appeared first on PYMNTS.com.",
            "source": "PYMNTS",
            "published": "2026-05-03T23:52:38+00:00",
            "category": "fintech",
            "subsection": "Platforms & Products"
          },
          {
            "id": "88aba16e7ae384caab25fe0552217a7e",
            "title": "Brazil Outlaws Crypto Remittances From FX Companies",
            "url": "https://www.pymnts.com/cryptocurrency/2026/brazil-outlaws-crypto-remittances-from-fx-companies/",
            "summary": "Brazil has forbidden electronic foreign exchange (eFX) companies from using cryptocurrencies to settle overseas remittances.  That\u2019s according to a new resolution from the country\u2019s central bank, published last week and flagged Sunday (May 3) in a report by CoinDesk. Under the new rules, set to go into effect Oct. 1, payments between a Brazilian [&#8230;]\nThe post Brazil Outlaws Crypto Remittances From FX Companies appeared first on PYMNTS.com.",
            "source": "PYMNTS",
            "published": "2026-05-03T23:13:26+00:00",
            "category": "fintech",
            "subsection": "Platforms & Products"
          },
          {
            "id": "57d6ed30bf395d6dac663ecab706357d",
            "title": "Crypto Firms Keep Stablecoin Rewards Under Senate Deal",
            "url": "https://www.pymnts.com/cryptocurrency/2026/crypto-firms-keep-stablecoin-rewards-under-senate-deal/",
            "summary": "Lawmakers have reportedly struck an important agreement on the way toward finalizing new cryptocurrency legislation.  As Punchbowl News reported Friday (May 1), Sens. Thom Tillis, R-N.C., and Angela Alsobrooks, D-Md., have reached a compromise to restrict stablecoin yield and rewards, a key development as the Senate plans a crypto markup later this month. A [&#8230;]\nThe post Crypto Firms Keep Stablecoin Rewards Under Senate Deal appeared first on PYMNTS.com.",
            "source": "PYMNTS",
            "published": "2026-05-03T22:11:56+00:00",
            "category": "fintech",
            "subsection": "Platforms & Products"
          },
          {
            "id": "521efb99e6c714e7ebec280650dbea37",
            "title": "Apple\u2019s Stance on Vibe Coding Apps Leaves Startups Frustrated",
            "url": "https://www.pymnts.com/apple/2026/apples-stance-on-vibe-coding-apps-leaves-startups-frustrated/",
            "summary": "Apple\u2019s approach to so-called \u201cvibe coding\u201d apps has reportedly triggered complaints among startups and investors.  As the Financial Times (FT) reported Sunday (May 3), the issue centers around what these companies argue is Apple\u2019s erratic approach to applying App Store rules. This is happening amid a rise in artificial intelligence tools designed to make [&#8230;]\nThe post Apple&#8217;s Stance on Vibe Coding Apps Leaves Startups Frustrated appeared first on PYMNTS.com.",
            "source": "PYMNTS",
            "published": "2026-05-03T21:30:19+00:00",
            "category": "fintech",
            "subsection": "Platforms & Products"
          },
          {
            "id": "8b42888e4c1e184a1ed6129cd27d1194",
            "title": "GameStop Makes $55 Billion Bid to Acquire eBay",
            "url": "https://www.pymnts.com/acquisitions/2026/gamestop-eyes-ebay-acquisition-to-become-100-billion-company/",
            "summary": "GameStop says it has made a $55 billion proposal to acquire eBay.  The video game retailer announced Sunday (May 3) it had submitted a non-binding proposal to acquire 100% of the online marketplace. Following closing, GameStop CEO Ryan Cohen would serve as chief executive of the new combined company. In its letter to eBay, [&#8230;]\nThe post GameStop Makes $55 Billion Bid to Acquire eBay appeared first on PYMNTS.com.",
            "source": "PYMNTS",
            "published": "2026-05-03T20:44:32+00:00",
            "category": "fintech",
            "subsection": "Platforms & Products"
          },
          {
            "id": "6456af4e6eb519c001a976c93539e1e6",
            "title": "Meta Acquires ARI to Fuel Humanoid Robot Push",
            "url": "https://www.pymnts.com/meta/2026/meta-acquires-ari-to-fuel-humanoid-robot-push/",
            "summary": "Meta has acquired Assured Robot Intelligence (ARI), a startup developing artificial intelligence models for general-purpose, humanoid robots.  Xiaolong Wang, who co-founded ARI with Lerrel Pinto, shared news of the acquisition in a Friday (May 1) post on X. \u201cExcited to share that Assured Robot Intelligence (ARI) has joined [Meta] to help build the future [&#8230;]\nThe post Meta Acquires ARI to Fuel Humanoid Robot Push appeared first on PYMNTS.com.",
            "source": "PYMNTS",
            "published": "2026-05-03T20:21:08+00:00",
            "category": "fintech",
            "subsection": "Platforms & Products"
          }
        ],
        "Regulation": [
          {
            "id": "1f91ef990e6111d1bb129ca6b1118215",
            "title": "A Couple Million Lines of Haskell: Production Engineering at Mercury",
            "url": "https://blog.haskell.org/a-couple-million-lines-of-haskell/",
            "summary": "What it takes to run 2 million lines of Haskell in production at a fintech company serving 300,000 businesses.",
            "source": "Haskell.org",
            "published": "2026-05-03T00:01:14Z",
            "category": "fintech",
            "subsection": "Regulation"
          },
          {
            "id": "3d073724a2e1f8dfe49c47b781dcd8ff",
            "title": "Top B-schools see pay surge as hiring picks up",
            "url": "https://economictimes.indiatimes.com/industry/services/education/top-b-schools-see-pay-surge-as-hiring-picks-up/articleshow/130722357.cms",
            "summary": "Top Indian business schools report improved placement packages for the 2026 batch. Consulting and finance sectors are driving this growth. While technology hiring has scaled down, overall recruiter numbers have increased. This indicates a selective recovery i\u2026",
            "source": "The Times of India",
            "published": "2026-05-03T00:00:00Z",
            "category": "fintech",
            "subsection": "Regulation"
          },
          {
            "id": "8793b3ba376b21e2067498f6349e77c9",
            "title": "Top B-schools see pay surge as hiring picks up",
            "url": "https://economictimes.indiatimes.com/jobs/fresher/top-b-schools-see-pay-surge-as-hiring-picks-up/articleshow/130722357.cms",
            "summary": "Top Indian business schools report improved placement packages for the 2026 batch. Consulting and finance sectors are driving this growth. While technology hiring has scaled down, overall recruiter numbers have increased. This indicates a selective recovery i\u2026",
            "source": "The Times of India",
            "published": "2026-05-03T00:00:00Z",
            "category": "fintech",
            "subsection": "Regulation"
          },
          {
            "id": "cc32fbd7c6a8e95c6ac10c0c18fe3199",
            "title": "I battled self-doubt to succeed \u2014 Double first-class graduate, Ezeaka",
            "url": "https://punchng.com/i-battled-self-doubt-to-succeed-double-first-class-graduate-ezeaka/",
            "summary": "Precious Ezeaka, a double first-class graduate, shares her journey of overcoming self-doubt with consistency and faith to succeed in law school. Learn her\n\nRead More: https://punchng.com/i-battled-self-doubt-to-succeed-double-first-class-graduate-ezeaka/",
            "source": "The Punch",
            "published": "2026-05-02T23:23:46Z",
            "category": "fintech",
            "subsection": "Regulation"
          },
          {
            "id": "4dc64973e60ec50c0635c3c3cb657e2a",
            "title": "Stifel Raises Microsoft (MSFT) Price Target, Keeps Hold Rating",
            "url": "https://finance.yahoo.com/markets/stocks/articles/stifel-raises-microsoft-msft-price-223919733.html",
            "summary": "Microsoft Corporation (NASDAQ:MSFT) is one of the 10 Best American Tech Stocks to Buy. On April 30, Stifel increased its price target on Microsoft...",
            "source": "Yahoo Entertainment",
            "published": "2026-05-02T22:39:19Z",
            "category": "fintech",
            "subsection": "Regulation"
          }
        ]
      }
    }
  }
}